interfacy_cli/__init__.py
interfacy_cli/core.py
interfacy_cli/exceptions.py
interfacy_cli/flag_generator.py
interfacy_cli/themes.py
interfacy_cli/util.py
interfacy_cli/argparse_backend/__init__.py
interfacy_cli/argparse_backend/argparser.py
interfacy_cli/argparse_backend/argument_parser.py
interfacy_cli/argparse_backend/help_formatter.py
interfacy_cli/argparse_backend/runner.py
interfacy_cli/argparse_backend/utils.py
interfacy_cli/click_backend/click_parser.py
interfacy_cli-0.2.2.dist-info/LICENSE
interfacy_cli-0.2.2.dist-info/METADATA
interfacy_cli-0.2.2.dist-info/WHEEL
interfacy_cli-0.2.2.dist-info/top_level.txt
interfacy_cli-0.2.2.dist-info/RECORD
