Metadata-Version: 2.2
Name: interfacy-cli
Version: 0.2.2
Author-email: Žiga Ivanšek <ziga.ivansek@gmail.com>
Project-URL: Repository, https://github.com/zigai/obj-inspect
Keywords: interfacy,cli,command-line,argparse,cli-generator,cli-builder,cli-framework
Classifier: Intended Audience :: Developers
Classifier: License :: OSI Approved :: MIT License
Classifier: Operating System :: OS Independent
Classifier: Programming Language :: Python
Classifier: Programming Language :: Python :: 3.10
Classifier: Programming Language :: Python :: 3.11
Classifier: Programming Language :: Python :: 3 :: Only
Classifier: Topic :: Software Development :: Libraries :: Python Modules
Requires-Python: >=3.10
License-File: LICENSE
Requires-Dist: nested_argparse==0.1.2
Requires-Dist: stdl>=0.5.6
Requires-Dist: objinspect>=0.2.14
Requires-Dist: strto>=0.1.7
Provides-Extra: full
Requires-Dist: argcomplete; extra == "full"
Provides-Extra: test
Requires-Dist: pytest; extra == "test"
Provides-Extra: dev
Requires-Dist: black; extra == "dev"
Requires-Dist: pytest; extra == "dev"
Requires-Dist: flake8; extra == "dev"
